bottle_stone.py
bottle_stone-0.1.0.dist-info/DESCRIPTION.rst
bottle_stone-0.1.0.dist-info/METADATA
bottle_stone-0.1.0.dist-info/RECORD
bottle_stone-0.1.0.dist-info/WHEEL
bottle_stone-0.1.0.dist-info/metadata.json
bottle_stone-0.1.0.dist-info/top_level.txt
