Metadata-Version: 1.1
Name: bottle-stone
Version: 0.1.0
Summary: Plugin to use the Stone IDL with Bottle.
Home-page: https://github.com/braincore/bottle-stone
Author: Ken Elkabany
Author-email: ken@elkabany.com
License: MIT
Platform: CPython 2.7
Platform: CPython 3.4
Platform: CPython 3.5
Classifier: Development Status :: 4 - Beta
Classifier: Intended Audience :: Developers
Classifier: License :: OSI Approved :: MIT License
Classifier: Topic :: Internet :: WWW/HTTP :: WSGI :: Application
Classifier: Topic :: Internet :: WWW/HTTP :: WSGI :: Middleware
Classifier: Topic :: Internet :: WWW/HTTP :: WSGI :: Server
Classifier: Topic :: Software Development :: Libraries :: Application Frameworks
Classifier: Programming Language :: Python :: 2.7
Classifier: Programming Language :: Python :: 3
Classifier: Programming Language :: Python :: 3.4
Classifier: Programming Language :: Python :: 3.5
